{
  "openapi": "3.0.2",
  "paths": {},
  "info": {
    "title": "",
    "version": ""
  },
  "components": {
    "schemas": {
      "PatientTelecom": {
        "title": "PatientTelcom",
        "description": "patient telecom communication",
        "type": "object",
        "properties": {
          "telecomSystem": {
            "type": "string",
            "maxLength": 255
          },
          "telecomUse": {
            "type": "string",
            "maxLength": 255
          },
          "telecomValue": {
            "type": "string",
            "maxLength": 255
          }
        },
        "required": [
          "telecomSystem",
          "telecomUse",
          "telecomValue"
        ]
      }
    }
  }
}
